terminal_snake/__init__.py
terminal_snake/__main__.py
terminal_snake/game.py
terminal_snake/theme.py
terminal_snake-0.6.0.dist-info/WHEEL
terminal_snake-0.6.0.dist-info/METADATA
terminal_snake-0.6.0.dist-info/RECORD
